mjoindices/__init__.py
mjoindices/_version.py
mjoindices/empirical_orthogonal_functions.py
mjoindices/evaluation_tools.py
mjoindices/olr_handling.py
mjoindices/principal_components.py
mjoindices/tools.py
mjoindices/omi/__init__.py
mjoindices/omi/omi_calculator.py
mjoindices/omi/postprocessing_original_kiladis2014.py
mjoindices/omi/postprocessing_rotation_approach.py
mjoindices/omi/quick_temporal_filter.py
mjoindices/omi/wheeler_kiladis_mjo_filter.py
mjoindices/omi/sign_reference/eof1/eof001.txt
mjoindices/omi/sign_reference/eof2/eof001.txt
mjoindices-1.4.1.dist-info/LICENSE
mjoindices-1.4.1.dist-info/METADATA
mjoindices-1.4.1.dist-info/WHEEL
mjoindices-1.4.1.dist-info/top_level.txt
mjoindices-1.4.1.dist-info/RECORD
