Metadata-Version: 2.1
Name: mjoindices
Version: 1.4.1
Summary: Calculation of indices that describe the Madden-Julian-Oscillation (only OMI by now)
Home-page: https://github.com/cghoffmann/mjoindices
Author: Christoph G. Hoffmann
Author-email: christoph.hoffmann@uni-greifswald.de
License: GNU General Public License v3
License-File: LICENSE
Requires-Dist: numpy
Requires-Dist: pandas
Requires-Dist: scipy
Requires-Dist: matplotlib
Requires-Dist: netCDF4
Provides-Extra: dev
Requires-Dist: build ; extra == 'dev'
Requires-Dist: pytest ; extra == 'dev'
Requires-Dist: pytest-pep8 ; extra == 'dev'
Requires-Dist: tox ; extra == 'dev'
Requires-Dist: sphinx ; extra == 'dev'
Requires-Dist: m2r2 ; extra == 'dev'
Requires-Dist: sphinx-rtd-theme ; extra == 'dev'
Requires-Dist: twine ; extra == 'dev'
Provides-Extra: full_func
Requires-Dist: eofs ; extra == 'full_func'
Requires-Dist: xarray ; extra == 'full_func'
